callgraph/__init__.py
callgraph/__main__.py
callgraph/callgraph.py
callgraph/core.py
callgraph/render.py
cmd_call_graph-1.2.1.dist-info/LICENSE
cmd_call_graph-1.2.1.dist-info/METADATA
cmd_call_graph-1.2.1.dist-info/WHEEL
cmd_call_graph-1.2.1.dist-info/entry_points.txt
cmd_call_graph-1.2.1.dist-info/top_level.txt
cmd_call_graph-1.2.1.dist-info/RECORD
