Metadata-Version: 2.1
Name: cmd-call-graph
Version: 1.2.1
Summary: A simple tool to generate a call graph for calls within Windows CMD (batch) files.
Home-page: https://github.com/Microsoft/cmd-call-graph
Author: Andrea Spadaccini
Author-email: andrea.spadaccini@gmail.com
License: MIT
Platform: UNKNOWN
Classifier: Development Status :: 5 - Production/Stable
Classifier: Environment :: Console
Classifier: Intended Audience :: Developers
Classifier: License :: OSI Approved :: MIT License
Classifier: Operating System :: OS Independent
Classifier: Topic :: Scientific/Engineering :: Visualization
Classifier: Topic :: Software Development :: Documentation
